slp/__init__.py
slp/config/__init__.py
slp/config/config_parser.py
slp/config/multimodal.py
slp/config/nlp.py
slp/config/omegaconf.py
slp/data/__init__.py
slp/data/cmusdk.py
slp/data/collators.py
slp/data/corpus.py
slp/data/datasets.py
slp/data/multimodal.py
slp/data/transforms.py
slp/modules/__init__.py
slp/modules/attention.py
slp/modules/classifier.py
slp/modules/embed.py
slp/modules/feedforward.py
slp/modules/fuse.py
slp/modules/m3.py
slp/modules/mmdrop.py
slp/modules/multimodal.py
slp/modules/norm.py
slp/modules/regularization.py
slp/modules/rnn.py
slp/modules/symattention.py
slp/modules/transformer.py
slp/plbind/__init__.py
slp/plbind/dm.py
slp/plbind/helpers.py
slp/plbind/metrics.py
slp/plbind/module.py
slp/plbind/trainer.py
slp/util/__init__.py
slp/util/log.py
slp/util/mosei.py
slp/util/pytorch.py
slp/util/system.py
slp/util/tuning.py
slp/util/types.py
slp-1.2.1.dist-info/LICENSE
slp-1.2.1.dist-info/WHEEL
slp-1.2.1.dist-info/METADATA
slp-1.2.1.dist-info/RECORD
