Metadata-Version: 2.1
Name: slp
Version: 1.2.1
Summary: Speech, Language and Multimodal Processing models and utilities in PyTorch
Home-page: https://georgepar.github.io/slp
License: MIT
Keywords: pytorch,nlp,multimodal
Author: Giorgos Paraskevopoulos
Author-email: geopar@central.ntua.gr
Requires-Python: >=3.8,<4.0
Classifier: Development Status :: 3 - Alpha
Classifier: Environment :: Console
Classifier: Environment :: GPU :: NVIDIA CUDA
Classifier: Intended Audience :: Developers
Classifier: Intended Audience :: Science/Research
Classifier: License :: OSI Approved :: MIT License
Classifier: Operating System :: POSIX :: Linux
Classifier: Programming Language :: Python :: 3
Classifier: Programming Language :: Python :: 3.8
Classifier: Programming Language :: Python :: 3.9
Classifier: Topic :: Education
Classifier: Topic :: Scientific/Engineering :: Artificial Intelligence
Requires-Dist: aiohttp (>=3.7.4,<4.0.0)
Requires-Dist: gym (>=0.18.0,<0.19.0)
Requires-Dist: h5py (>=3.2.1,<4.0.0)
Requires-Dist: loguru (>=0.5.3,<0.6.0)
Requires-Dist: matplotlib (>=3.3.4,<4.0.0)
Requires-Dist: mike (>=0.6.0,<0.7.0)
Requires-Dist: nltk (>=3.5,<4.0)
Requires-Dist: numpy (>=1.19.5,<2.0.0)
Requires-Dist: omegaconf (>=2.0.6,<3.0.0)
Requires-Dist: optuna (>=2.6.0,<3.0.0)
Requires-Dist: pytorch-lightning (>=1.2.0,<2.0.0)
Requires-Dist: pytorch-lightning-bolts (>=0.3.0,<0.4.0)
Requires-Dist: pytorch-nlp (==0.4.1)
Requires-Dist: ray[tune] (>=1.2.0,<2.0.0)
Requires-Dist: requests (>=2.25.1,<3.0.0)
Requires-Dist: scikit-learn (>=0.24.1,<0.25.0)
Requires-Dist: scipy (>=1.6.1,<2.0.0)
Requires-Dist: sentencepiece (>=0.1.95,<0.2.0)
Requires-Dist: spacy (>=3.0.3,<4.0.0)
Requires-Dist: toml (>=0.10.2,<0.11.0)
Requires-Dist: toolz (>=0.11.1,<0.12.0)
Requires-Dist: torch (>=1.7.1,<2.0.0)
Requires-Dist: torchmetrics (>=0.3.2,<0.4.0)
Requires-Dist: torchvision (>=0.8.2,<0.9.0)
Requires-Dist: tqdm (>=4.57.0,<5.0.0)
Requires-Dist: transformers (==4.3.0)
Requires-Dist: ujson (>=4.0.2,<5.0.0)
Requires-Dist: validators (>=0.18.2,<0.19.0)
Requires-Dist: wandb (>=0.10.20,<0.11.0)
Project-URL: Repository, https://github.com/georgepar/slp
